{"doc":" 房源特色Service接口\n\n @author house\n @date 2024-03-05\n","fields":[],"enumConstants":[],"methods":[{"name":"queryById","paramTypes":["java.lang.Long"],"doc":" 查询房源特色\n"},{"name":"queryPageList","paramTypes":["com.house.core.domain.bo.HouseFeatureBo","com.house.common.core.domain.PageQuery"],"doc":" 查询房源特色列表\n"},{"name":"queryList","paramTypes":["com.house.core.domain.bo.HouseFeatureBo"],"doc":" 查询房源特色列表\n"},{"name":"insertByBo","paramTypes":["com.house.core.domain.bo.HouseFeatureBo"],"doc":" 新增房源特色\n"},{"name":"updateByBo","paramTypes":["com.house.core.domain.bo.HouseFeatureBo"],"doc":" 修改房源特色\n"},{"name":"deleteWithValidByIds","paramTypes":["java.util.Collection","java.lang.Boolean"],"doc":" 校验并批量删除房源特色信息\n"}],"constructors":[]}